msgpipe/__init__.py
msgpipe-0.1.1.dist-info/METADATA
msgpipe-0.1.1.dist-info/WHEEL
msgpipe-0.1.1.dist-info/RECORD
