Metadata-Version: 2.1
Name: msgpipe
Version: 0.1.1
Summary: Simple IPC worker request framework
Author: Wilson Lin
Author-email: pypi@wilsonl.in
Requires-Python: >=3.8,<4.0
Classifier: Programming Language :: Python :: 3
Classifier: Programming Language :: Python :: 3.8
Classifier: Programming Language :: Python :: 3.9
Classifier: Programming Language :: Python :: 3.10
Classifier: Programming Language :: Python :: 3.11
Classifier: Programming Language :: Python :: 3.12
Requires-Dist: msgpack (>=1.0.8,<2.0.0)
